archdoc_toolkit/__init__.py
archdoc_toolkit/data.py
archdoc_toolkit/documentation_generator.py
archdoc_toolkit-0.1.1.dist-info/METADATA
archdoc_toolkit-0.1.1.dist-info/WHEEL
archdoc_toolkit-0.1.1.dist-info/RECORD
